odoo/addons/report_substitute/README.rst
odoo/addons/report_substitute/__init__.py
odoo/addons/report_substitute/__manifest__.py
odoo/addons/report_substitute/demo/action_report.xml
odoo/addons/report_substitute/i18n/es.po
odoo/addons/report_substitute/i18n/it.po
odoo/addons/report_substitute/i18n/report_substitute.pot
odoo/addons/report_substitute/models/__init__.py
odoo/addons/report_substitute/models/ir_actions_report.py
odoo/addons/report_substitute/models/ir_actions_report_substitution_rule.py
odoo/addons/report_substitute/models/mail_thread.py
odoo/addons/report_substitute/readme/CONTRIBUTORS.md
odoo/addons/report_substitute/readme/DESCRIPTION.md
odoo/addons/report_substitute/readme/ROADMAP.md
odoo/addons/report_substitute/readme/USAGE.md
odoo/addons/report_substitute/security/ir_actions_report_substitution_rule.xml
odoo/addons/report_substitute/static/description/icon.png
odoo/addons/report_substitute/static/description/index.html
odoo/addons/report_substitute/static/src/js/action_manager.esm.js
odoo/addons/report_substitute/tests/__init__.py
odoo/addons/report_substitute/tests/test_report_substitute.py
odoo/addons/report_substitute/views/ir_actions_report.xml
odoo_addon_report_substitute-18.0.1.0.0.7.dist-info/METADATA
odoo_addon_report_substitute-18.0.1.0.0.7.dist-info/WHEEL
odoo_addon_report_substitute-18.0.1.0.0.7.dist-info/top_level.txt
odoo_addon_report_substitute-18.0.1.0.0.7.dist-info/RECORD
